README
setup.py
Spider_haoyun/DataFormat.py
Spider_haoyun/Paser.py
Spider_haoyun/PinYin.py
Spider_haoyun/__init__.py
Spider_haoyun/connect_db.py
Spider_haoyun/databases.py
Spider_haoyun.egg-info/PKG-INFO
Spider_haoyun.egg-info/SOURCES.txt
Spider_haoyun.egg-info/dependency_links.txt
Spider_haoyun.egg-info/requires.txt
Spider_haoyun.egg-info/top_level.txt