Metadata-Version: 1.2
Name: Spider-haoyun
Version: 1.0.1
Summary: spider utils
Home-page: https://www.python.org/
Author: haoyun
Author-email: 1469779169@qq.com
License: MIT
Project-URL: Documentation, https://packaging.python.org/tutorials/distributing-packages/
Project-URL: Funding, https://donate.pypi.org
Project-URL: Source, https://github.com/pypa/sampleproject/
Project-URL: Tracker, https://github.com/pypa/sampleproject/issues
Keywords: ga nn
Platform: UNKNOWN
Requires-Python: >=3
